LICENSE
MANIFEST.in
setup.py
contentbus/__init__.py
contentbus/exceptions.py
contentbus/version.py
contentbus.egg-info/PKG-INFO
contentbus.egg-info/SOURCES.txt
contentbus.egg-info/dependency_links.txt
contentbus.egg-info/top_level.txt
contentbus/match/__init__.py
contentbus/match/operator.py