Metadata-Version: 1.0
Name: contentbus
Version: 0.0.1
Summary: Content-based bus
Home-page: http://code.google.com/p/contentbus
Author: Alberto Donato
Author-email: <alberto.donato@gmail.com>
License: GPL
Download-URL: http://code.google.com/p/contentbus/downloads/list
Keywords: content content-based bus publish subscribe
Platform: UNKNOWN
Classifier: Development Status :: 2 - Pre-Alpha
Classifier: Intended Audience :: Developers
Classifier: License :: OSI Approved :: GNU General Public License (GPL)
Classifier: Operating System :: OS Independent
Classifier: Programming Language :: Python
Classifier: Topic :: Software Development :: Libraries :: Application Frameworks
Classifier: Topic :: Software Development :: Libraries :: Python Modules
